selic/__init__.py
selic-0.1.0.dist-info/WHEEL
selic-0.1.0.dist-info/METADATA
selic-0.1.0.dist-info/RECORD
