Metadata-Version: 2.1
Name: selic
Version: 0.1.0
Summary: Fetch SELIC data
License: MIT
Author: tilacog
Author-email: tilacog@protonmail.com
Requires-Python: >=3.8,<4.0
Classifier: License :: OSI Approved :: MIT License
Classifier: Programming Language :: Python :: 3
Classifier: Programming Language :: Python :: 3.8
Requires-Dist: bs4 (>=0.0.1,<0.0.2)
Requires-Dist: requests (>=2.25.0,<3.0.0)
